mas/cli/__init__.py
mas/cli/cli.py
mas/cli/displayMixins.py
mas/cli/gencfg.py
mas/cli/validators.py
mas/cli/aiservice/install/__init__.py
mas/cli/aiservice/install/app.py
mas/cli/aiservice/install/argBuilder.py
mas/cli/aiservice/install/argParser.py
mas/cli/aiservice/install/params.py
mas/cli/aiservice/install/summarizer.py
mas/cli/aiservice/upgrade/__init__.py
mas/cli/aiservice/upgrade/app.py
mas/cli/aiservice/upgrade/argParser.py
mas/cli/install/__init__.py
mas/cli/install/app.py
mas/cli/install/argBuilder.py
mas/cli/install/argParser.py
mas/cli/install/catalogs.py
mas/cli/install/params.py
mas/cli/install/summarizer.py
mas/cli/install/settings/__init__.py
mas/cli/install/settings/additionalConfigs.py
mas/cli/install/settings/db2Settings.py
mas/cli/install/settings/kafkaSettings.py
mas/cli/install/settings/manageSettings.py
mas/cli/install/settings/mongodbSettings.py
mas/cli/templates/facilities-configs.yml.j2
mas/cli/templates/ibm-mas-tekton.yaml
mas/cli/templates/jdbccfg.yml.j2
mas/cli/templates/suite_mongocfg.yml.j2
mas/cli/templates/pod-templates/best-effort/ibm-data-dictionary-assetdatadictionary.yml
mas/cli/templates/pod-templates/best-effort/ibm-mas-bascfg.yml
mas/cli/templates/pod-templates/best-effort/ibm-mas-coreidp.yml
mas/cli/templates/pod-templates/best-effort/ibm-mas-iot-actions.yml
mas/cli/templates/pod-templates/best-effort/ibm-mas-iot-auth.yml
mas/cli/templates/pod-templates/best-effort/ibm-mas-iot-datapower.yml
mas/cli/templates/pod-templates/best-effort/ibm-mas-iot-devops.yml
mas/cli/templates/pod-templates/best-effort/ibm-mas-iot-dm.yml
mas/cli/templates/pod-templates/best-effort/ibm-mas-iot-dsc.yml
mas/cli/templates/pod-templates/best-effort/ibm-mas-iot-edgeconfig.yml
mas/cli/templates/pod-templates/best-effort/ibm-mas-iot-fpl.yml
mas/cli/templates/pod-templates/best-effort/ibm-mas-iot-guardian.yml
mas/cli/templates/pod-templates/best-effort/ibm-mas-iot-iot.yml
mas/cli/templates/pod-templates/best-effort/ibm-mas-iot-mbgx.yml
mas_cli-19.0.0.dist-info/METADATA
mas_cli-19.0.0.dist-info/WHEEL
mas_cli-19.0.0.dist-info/top_level.txt
mas_cli-19.0.0.dist-info/RECORD
