Metadata-Version: 2.4
Name: mas-cli
Version: 19.0.0
Summary: Python Admin CLI for Maximo Application Suite
Home-page: https://github.com/ibm-mas/cli
Author: David Parker
Author-email: parkerda@uk.ibm.com
License: Eclipse Public License - v1.0
Classifier: Development Status :: 4 - Beta
Classifier: Intended Audience :: Developers
Classifier: Operating System :: Microsoft :: Windows
Classifier: Operating System :: POSIX :: Linux
Classifier: Programming Language :: Python
Classifier: Programming Language :: Python :: 3.12
Classifier: Topic :: Communications
Classifier: Topic :: Internet
Classifier: Topic :: Software Development :: Libraries :: Python Modules
Requires-Dist: mas-devops>=5.2.0
Requires-Dist: halo
Requires-Dist: prompt_toolkit
Requires-Dist: openshift
Requires-Dist: kubernetes==33.1.0
Requires-Dist: tabulate
Provides-Extra: dev
Requires-Dist: build; extra == "dev"
Requires-Dist: flake8; extra == "dev"
Requires-Dist: pytest; extra == "dev"
Requires-Dist: pyinstaller; extra == "dev"
Dynamic: author
Dynamic: author-email
Dynamic: classifier
Dynamic: description
Dynamic: home-page
Dynamic: license
Dynamic: provides-extra
Dynamic: requires-dist
Dynamic: summary
